repomix-0.3.4.dist-info/METADATA
repomix-0.3.4.dist-info/WHEEL
repomix-0.3.4.dist-info/entry_points.txt
repomix/__init__.py
repomix/__main__.py
repomix/cli/__init__.py
repomix/cli/actions/__init__.py
repomix/cli/actions/default_action.py
repomix/cli/actions/init_action.py
repomix/cli/actions/remote_action.py
repomix/cli/actions/version_action.py
repomix/cli/cli_print.py
repomix/cli/cli_run.py
repomix/cli/cli_spinner.py
repomix/cli/types.py
repomix/config/__init__.py
repomix/config/config_load.py
repomix/config/config_schema.py
repomix/config/default_ignore.py
repomix/config/global_directory.py
repomix/core/file/__init__.py
repomix/core/file/file_collect.py
repomix/core/file/file_manipulate.py
repomix/core/file/file_process.py
repomix/core/file/file_search.py
repomix/core/file/file_stdin.py
repomix/core/file/file_types.py
repomix/core/file/git_command.py
repomix/core/file/permission_check.py
repomix/core/file/truncate_base64.py
repomix/core/output/__init__.py
repomix/core/output/output_generate.py
repomix/core/output/output_style_decorate.py
repomix/core/output/output_styles/__init__.py
repomix/core/output/output_styles/_utils.py
repomix/core/output/output_styles/markdown_style.py
repomix/core/output/output_styles/plain_style.py
repomix/core/output/output_styles/xml_style.py
repomix/core/packager/copy_to_clipboard.py
repomix/core/repo_processor.py
repomix/core/security/__init__.py
repomix/core/security/security_check.py
repomix/core/tree_sitter/__init__.py
repomix/core/tree_sitter/ext2lang.py
repomix/core/tree_sitter/lang2query.py
repomix/core/tree_sitter/language_parser.py
repomix/core/tree_sitter/load_language.py
repomix/core/tree_sitter/parse_file.py
repomix/core/tree_sitter/parse_strategies/__init__.py
repomix/core/tree_sitter/parse_strategies/default_parse_strategy.py
repomix/core/tree_sitter/parse_strategies/go_parse_strategy.py
repomix/core/tree_sitter/parse_strategies/parse_strategy.py
repomix/core/tree_sitter/parse_strategies/python_parse_strategy.py
repomix/core/tree_sitter/parse_strategies/typescript_parse_strategy.py
repomix-0.3.4.dist-info/RECORD
