Metadata-Version: 2.1
Name: repomix
Version: 0.3.4
Summary: A tool for analyzing and summarizing code repositories
Author-Email: Anderson <andersonby@163.com>
License: MIT
Requires-Python: >=3.10
Requires-Dist: questionary>=2.0.1
Requires-Dist: chardet>=5.2.0
Requires-Dist: pyperclip>=1.9.0
Requires-Dist: tiktoken>=0.8.0
Requires-Dist: detect-secrets>=1.5.0
Requires-Dist: mcp>=1.2.0
Requires-Dist: tree-sitter>=0.20.0
Requires-Dist: tree-sitter-python>=0.20.0
Requires-Dist: tree-sitter-javascript>=0.20.0
